timing/__init__.py
timing/api.py
timing/cli.py
timing/config.py
timing/engine.py
timing/models.py
timing/report/__init__.py
timing/report/builder.py
timing/report/charts.py
timing/report/data.py
timing/report/html.py
timing/report/tables.py
timing/storage/__init__.py
timing/storage/base.py
timing/storage/sqlite.py
tmng-1.2.1.dist-info/METADATA
tmng-1.2.1.dist-info/WHEEL
tmng-1.2.1.dist-info/entry_points.txt
tmng-1.2.1.dist-info/top_level.txt
tmng-1.2.1.dist-info/RECORD
