Metadata-Version: 2.4
Name: tmng
Version: 1.2.1
Summary: A framework-agnostic, process-safe, local performance timer for Python applications.
Author-email: Luis Guilherme <lgpelin92@gmail.com>
License: MIT License
Project-URL: Homepage, https://github.com/your-repo/py-timing-tool
Project-URL: Bug Tracker, https://github.com/your-repo/py-timing-tool/issues
Classifier: Programming Language :: Python :: 3
Classifier: Operating System :: OS Independent
Requires-Python: >=3.8
Requires-Dist: pydantic
Requires-Dist: pandas
Requires-Dist: plotly
Requires-Dist: typer[all]
Requires-Dist: rich
Requires-Dist: appdirs
Provides-Extra: dev
Requires-Dist: ruff; extra == "dev"
Requires-Dist: pytest; extra == "dev"
Requires-Dist: build; extra == "dev"
